LICENSE
MANIFEST.in
README
setup.py
version.py
rask_njord_brtools/__init__.py
rask_njord_brtools.egg-info/PKG-INFO
rask_njord_brtools.egg-info/SOURCES.txt
rask_njord_brtools.egg-info/dependency_links.txt
rask_njord_brtools.egg-info/requires.txt
rask_njord_brtools.egg-info/top_level.txt