Metadata-Version: 1.0
Name: rask-njord-brtools
Version: 0.0.14
Summary: Rask BRTools Client
Home-page: https://gitlab.com/vikingmakt/rask_njord_brtools
Author: Umgeher Torgersen
Author-email: me@umgeher.org
License: https://gitlab.com/vikingmakt/rask_njord_brtools/raw/master/LICENSE
Platform: UNKNOWN
